setup.py
./snapper.py
snapperbal.egg-info/PKG-INFO
snapperbal.egg-info/SOURCES.txt
snapperbal.egg-info/dependency_links.txt
snapperbal.egg-info/entry_points.txt
snapperbal.egg-info/requires.txt
snapperbal.egg-info/top_level.txt