Metadata-Version: 1.1
Name: snapperbal
Version: 1.1.1
Summary: Snapper balance from the confort of your terminal
Home-page: http://example.org/
Author: Filype Pereira
Author-email: pereira.filype@gmail.com
License: BSD
Platform: UNKNOWN
Classifier: Development Status :: 4 - Beta
Classifier: Environment :: Console
Classifier: Intended Audience :: End Users/Desktop
Classifier: License :: OSI Approved :: MIT License
Classifier: Operating System :: MacOS :: MacOS X
Classifier: Operating System :: Unix
Classifier: Operating System :: POSIX
Classifier: Programming Language :: Python
